zstar/__init__.py
zstar/calc_kappa.py
zstar/cli.py
zstar/deal_polar.py
zstar/gen_polar.py
zstar/get_wyckoff.py
zstar/group_modesDB.py
zstar/phonon_gen.py
zstar/phonon_post.py
zstar/read_irrep.py
zstar/stru_analyzer.py
zstar/verify_born_symmetry.py
zstar-0.0.7.dist-info/licenses/LICENSE
zstar-0.0.7.dist-info/METADATA
zstar-0.0.7.dist-info/WHEEL
zstar-0.0.7.dist-info/entry_points.txt
zstar-0.0.7.dist-info/top_level.txt
zstar-0.0.7.dist-info/RECORD
