Metadata-Version: 2.4
Name: zstar
Version: 0.0.7
Summary: Zstar: A code for calculations of Born effective charge and dielectric responses.
Author-email: Xudong Zhu <zhuxudong@ustc.edu.cn>
License: GPL-3.0
Project-URL: Homepage, https://github.com/xdzhu/zstar
Project-URL: Repository, https://github.com/xdzhu/zstar
Requires-Python: >=3.8
License-File: LICENSE
Requires-Dist: numpy>=1.26
Requires-Dist: PyYAML>=5.4
Requires-Dist: matplotlib>=3.3
Requires-Dist: spglib>=2.6.0
Requires-Dist: phonopy>=2.36
Requires-Dist: pymatgen>=2024.0.0
Dynamic: license-file
